MANIFEST.in
README
README.md
setup.py
deepmoon/__init__.py
deepmoon/artisanal.py
deepmoon/cuda.py
deepmoon/darknet.py
deepmoon/errors.py
deepmoon/four_test_errors.py
deepmoon/gan.py
deepmoon/main.py
deepmoon/missing_from_tensorflow.py
deepmoon/potemkin.py
deepmoon.egg-info/PKG-INFO
deepmoon.egg-info/SOURCES.txt
deepmoon.egg-info/dependency_links.txt
deepmoon.egg-info/entry_points.txt
deepmoon.egg-info/requires.txt
deepmoon.egg-info/top_level.txt