Metadata-Version: 1.0
Name: deepmoon
Version: 0.5.2
Summary: The deep learning framework from beyond the moon
Home-page: https://github.com/paulfitz/deepmoon
Author: Paul Fitzpatrick
Author-email: paulfitz@alum.mit.edu
License: UNKNOWN
Platform: UNKNOWN
